<?xml version="1.0" encoding="us-ascii"?>
<XML ID="EQInterfaceDefinitionLanguage">
  <Schema xmlns="EverQuestData" xmlns:dt="EverQuestDataTypes" />
  <Screen item="ZealMap">
    <RelativePosition>false</RelativePosition>
    <Location>
      <X>95</X>
      <Y>240</Y>
    </Location>
    <Size>
      <CX>421</CX>
      <CY>120</CY>
    </Size>
    <Style_VScroll>false</Style_VScroll>
    <Style_HScroll>false</Style_HScroll>
    <Style_Transparent>false</Style_Transparent>
    <DrawTemplate>WDT_Def2</DrawTemplate>
    <Style_Titlebar>false</Style_Titlebar>
    <Style_Closebox>false</Style_Closebox>
    <Style_Minimizebox>false</Style_Minimizebox>
    <Style_Border>true</Style_Border>
    <Style_Sizable>false</Style_Sizable>
  </Screen>
</XML>